wiim/__init__.py
wiim/__main__.py
wiim/__version__.py
wiim/consts.py
wiim/controller.py
wiim/discovery.py
wiim/endpoint.py
wiim/exceptions.py
wiim/handler.py
wiim/manufacturers.py
wiim/py.typed
wiim/wiim_device.py
wiim-0.0.5.dist-info/licenses/LICENSE
wiim-0.0.5.dist-info/METADATA
wiim-0.0.5.dist-info/WHEEL
wiim-0.0.5.dist-info/top_level.txt
wiim-0.0.5.dist-info/RECORD
